RTL_Verilog/verilog_files/asyncset.v
`timescale 1ns / 1ps
module asyncset(clk,d,aset,q);
input clk,d,aset;
output reg q;
always @(posedge clk or posedge aset)
begin
        if(aset)
                q<=1'b1;
        else
                q<=d;
end
endmodule

RTL_Verilog/verilog_files/asyncset_tb.v
`timescale 1ns / 1ps
module asyncset_tb;
reg clk,d,aset;
wire q;
asyncset asyncsetuut(clk,d,aset,q);
initial begin
	$dumpfile("asyncset_tb.vcd");
        $dumpvars(0,asyncset_tb);
        clk=0;
        aset=0;
        d=0;
        #120 $finish;
end
always #15 clk = ~clk;
always #20 aset = ~aset;
always #40 d = ~d;
endmodule

RTL_Verilog/verilog_files/asyncset_tb.vcd
$date
	Tue Aug 29 11:41:03 2023
$end
$version
	Icarus Verilog
$end
$timescale
	1ps
$end
$scope module asyncset_tb $end
$var wire 1 ! q $end
$var reg 1 " aset $end
$var reg 1 # clk $end
$var reg 1 $ d $end
$scope module asyncsetuut $end
$var wire 1 " aset $end
$var wire 1 # clk $end
$var wire 1 $ d $end
$var reg 1 ! q $end
$upscope $end
$upscope $end
$enddefinitions $end
#0
$dumpvars
0$
0#
0"
x!
$end
#15000
0!
1#
#20000
1!
1"
#30000
0#
#40000
0"
1$
#45000
1#
#60000
0#
1"
#75000
1#
#80000
0"
0$
#90000
0#
#100000
1"
#105000
1#
#120000
0#
0"
1$
