RTL_Verilog/verilog_files/mux.v
`timescale 1ns / 1ps

module mux(i0,i1,s,y);
input i0,i1,s;
output reg y;
always @(*) begin
	if(s) 
		y<=i1; 
	else
		y<=i0;
end
endmodule

RTL_Verilog/verilog_files/mux_tb.v
`timescale 1ns / 1ps

module mux_tb;
reg i0,i1,s;
wire y;

mux uut(i0,i1,s,y);

initial begin
	$dumpfile("mux_tb.vcd");
	$dumpvars(0,mux_tb);
	i0=0;i1=0;s=0; #100 $finish;end

always #10 i0 = ~i0;
always #20 i1 = ~i1;
always #40 s = ~s;

endmodule

RTL_Verilog/verilog_files/mux_tb.vcd
$date
	Tue Aug 29 10:49:43 2023
$end
$version
	Icarus Verilog
$end
$timescale
	1ps
$end
$scope module mux_tb $end
$var wire 1 ! y $end
$var reg 1 " i0 $end
$var reg 1 # i1 $end
$var reg 1 $ s $end
$scope module uut $end
$var wire 1 " i0 $end
$var wire 1 # i1 $end
$var wire 1 $ s $end
$var reg 1 ! y $end
$upscope $end
$upscope $end
$enddefinitions $end
#0
$dumpvars
0$
0#
0"
0!
$end
#10000
1!
1"
#20000
0!
0"
1#
#30000
1!
1"
#40000
0!
0"
0#
1$
#50000
1"
#60000
1!
0"
1#
#70000
1"
#80000
0!
0"
0#
0$
#90000
1!
1"
#100000
0!
0"
1#
