RTL_Verilog/verilog_files/sync_async_res.v
`timescale 1ns / 1ps
module sync_async_res(clk,d,sres,ares,q);
input clk,d,sres,ares;
output reg  q;

always @(posedge clk ,posedge ares)
begin
	if(ares)
		q<=1'b0;
	else if(sres)
		q<=1'b0;
	else
		q<=d;
end
endmodule

RTL_Verilog/verilog_files/sync_async_res_tb.v
`timescale 1ns / 1ps
module sync_async_res_tb;
reg clk,d,ares,sres;
wire q;
sync_async_res sasyncresuut(clk,d,sres,ares,q);
initial begin
	$dumpfile("sync_async_res_tb.vcd");
        $dumpvars(0,sync_async_res_tb);
        clk=0;
	sres=1;
        ares=0;
        d=0;
        #240 $finish;
end
always #10 clk = ~clk;
always #15 ares = ~ares;
always #15 sres = ~sres;
always #40 d = ~d;
endmodule

RTL_Verilog/verilog_files/sync_async_res_tb.vcd
$date
	Tue Aug 29 12:01:54 2023
$end
$version
	Icarus Verilog
$end
$timescale
	1ps
$end
$scope module sync_async_res_tb $end
$var wire 1 ! q $end
$var reg 1 " ares $end
$var reg 1 # clk $end
$var reg 1 $ d $end
$var reg 1 % sres $end
$scope module sasyncresuut $end
$var wire 1 " ares $end
$var wire 1 # clk $end
$var wire 1 $ d $end
$var wire 1 % sres $end
$var reg 1 ! q $end
$upscope $end
$upscope $end
$enddefinitions $end
#0
$dumpvars
1%
0$
0#
0"
x!
$end
#10000
0!
1#
#15000
0%
1"
#20000
0#
#30000
1#
1%
0"
#40000
0#
1$
#45000
0%
1"
#50000
1#
#60000
0#
1%
0"
#70000
1#
#75000
0%
1"
#80000
0#
0$
#90000
1#
1%
0"
#100000
0#
#105000
0%
1"
#110000
1#
#120000
0#
1%
0"
1$
#130000
1#
#135000
0%
1"
#140000
0#
#150000
1#
1%
0"
#160000
0#
0$
#165000
0%
1"
#170000
1#
#180000
0#
1%
0"
#190000
1#
#195000
0%
1"
#200000
0#
1$
#210000
1#
1%
0"
#220000
0#
#225000
0%
1"
#230000
1#
#240000
0#
1%
0"
0$
